<xml version="0.996" board="Microduino/mCookie-Core USB (32u4)[usb32u416m]" xmlns="http://www.w3.org/1999/xhtml"><block type="Microduino_KEYDigital" id="|mNb2kAv6MRa8bq4[!F3" x="73" y="1"><field name="KPin">2</field><field name="CHECK">SHORT_PRESS</field><statement name="DO"><block type="controls_if" id="Gp|gk+:XHdLc~+hR-d3."><value name="IF0"><block type="logic_compare" id="^7!FeN]XGr[])9bWLwfm"><field name="OP">LTE</field><value name="A"><block type="microduinoIRRactAnal" id="nOWHh4WIjPYwNa1smDK9"><field name="analogPin">A0</field><field name="action">distance</field></block></value><value name="B"><block type="math_number" id="I{NCui,59gwGZ@-+_g4I"><field name="NUM">500</field></block></value></block></value><statement name="DO0"><block type="base_delay" id="mib[C])?MCg%3a]`(f`;"><field name="UNIT">delay</field><value name="DELAY_TIME"><shadow type="math_number" id="Y(KUF)ShMp4}=jmrjirR"><field name="NUM">500</field></shadow></value><next><block type="BuzzerTone" id="2DG;o=O!,ZU=!+Qxx6%I"><value name="BuzzerPin"><shadow type="math_number" id="KGQJwZPvdha3]V{3-fjY"><field name="NUM">0</field></shadow></value><value name="Frequency"><shadow type="math_number" id="9UioyJ=MF])D:dR=(EJe"><field name="NUM">1300</field></shadow></value><next><block type="base_delay" id="piV_hgjh7:6?ShvSf.~#"><field name="UNIT">delay</field><value name="DELAY_TIME"><shadow type="math_number" id="f.nFc%~=HRq*D)ykN!:F"><field name="NUM">500</field></shadow></value><next><block type="BuzzerTone" id="KEavC1Yt)Uybu}~Aa_ui"><value name="BuzzerPin"><shadow type="math_number" id="NBB/K7l{B%L_1;s@5uy~"><field name="NUM">0</field></shadow></value><value name="Frequency"><shadow type="math_number" id="xgH.v3F):bA;d*I_}l7K"><field name="NUM">1000</field></shadow></value><next><block type="base_delay" id="A60UtxxnT5dKG0B{d)/D"><field name="UNIT">delay</field><value name="DELAY_TIME"><shadow type="math_number" id="St]k,e+5I@kPsZhv5U}K"><field name="NUM">500</field></shadow></value><next><block type="BuzzerNoTone" id="~KGGw8#t*rFlD`zznt:Q"><value name="BuzzerPin"><shadow type="math_number" id="gp_rbG~ea|{f4YOxwT{b"><field name="NUM">0</field></shadow></value></block></next></block></next></block></next></block></next></block></next></block></statement></block></statement></block></xml>